{
    "category":  "miss",
    "rank":  3,
    "folder":  "03-miss-vitoriabeatrizslv-403-likes-4-fotos-DSYyoSojTWp",
    "naming":  "Pasta: rank-categoria-perfil-likes-qtdfotos-codigo. Imagem: categoria-trabalho-rank-foto-numero-codigo.jpg.",
    "url":  "https://www.instagram.com/vitoriabeatrizslv/p/DSYyoSojTWp/",
    "likes":  "403",
    "comments":  "45",
    "probedImageCount":  4,
    "downloadedCount":  4,
    "rule":  "Trabalho aceito somente com 2+ fotos baixadas; preferencia para 3+.",
    "metaDescription":  "403 likes, 45 comments - vitoriabeatrizslv no December 17, 2025: \"A preliminar de gala não é apenas mais um desfile, é o primeiro contato para apresentar suas destrezas na passarela. Força, técnica, elegância, simpatia, empoderamento feminino e carisma se refletem em cada performance, buscando conquistar o olhar dos jurados e avançar rumo à etapa final!\n\nHoje, ela se apresenta com confiança, determinação e muita dedicação ao longo de sua trajetória como Miss Amazonas, carregando consigo a força da mulher amazonense, que se destaca e representa com orgulho diante de todo o Brasil 🇧🇷🙏🏻✨\n\nPara esse momento, ela surge em um vestido de gala imponente, com brilho marcante, recortes estratégicos e design sofisticado, que valoriza a silhueta e traduz força, feminilidade e presença cênica, produzido por @kaleb_aguiar 💙 \nMake up: @bentomakeup.hair \nHair: @embaixadora_dos_ruivos @casatalitacumi \nProdução: @jeitostew \nFotografia: @phbylara \nEstúdio: @produtoraversa\n\n@concursobelezasdobrasil @concursobelezasdoamazonas\". ",
    "classificationReason":  "Categoria atribuida pela sondagem textual/visual do Instagram; revisar legenda quando for usar na peca final.",
    "files":  [
                  {
                      "name":  "miss-trabalho-03-foto-01-DSYyoSojTWp.jpg",
                      "file":  "apps\\atelier-kaleb-aguiar\\public\\evidence\\instagram\\relaxed-works\\miss\\03-miss-vitoriabeatrizslv-403-likes-4-fotos-DSYyoSojTWp\\miss-trabalho-03-foto-01-DSYyoSojTWp.jpg",
                      "bytes":  942560,
                      "source":  "https://instagram.fmao1-1.fna.fbcdn.net/v/t51.82787-15/602831180_18089798999476747_365056888074276920_n.jpg?stp=dst-jpg_e35_tt6\u0026_nc_cat=109\u0026ig_cache_key=Mzc5MDAwMTc0NDg2OTQyNjIxNg%3D%3D.3-ccb7-5\u0026ccb=7-5\u0026_nc_sid=58cdad\u0026efg=eyJ2ZW5jb2RlX3RhZyI6IkNBUk9VU0VMX0lURU0ueHBpZHMuMTQ0MC5zZHIucmVndWxhcl9waG90by5DMyJ9\u0026_nc_ohc=1gUne5olWEMQ7kNvwHfqx-D\u0026_nc_oc=AdqeEJuJWL8mmiw0uS9PIqLIX1mBZGTbVcdgDnwPsKCQQH4MjrR7Qo48JT1A8PTQslgs8Z7wZL-Rpvs6dqIFnvxX\u0026_nc_ad=z-m\u0026_nc_cid=0\u0026_nc_zt=23\u0026_nc_ht=instagram.fmao1-1.fna\u0026_nc_gid=7lWsn8VloVAkg8CGImuoVg\u0026_nc_ss=7a22e\u0026oh=00_Af7C1huv7U10fi1gIh6X00_5NDHBy4jn0YhSA_jkuUiOVg\u0026oe=6A15088F",
                      "alt":  "Photo shared by Vitoria Beatriz on December 17, 2025 tagging @concursobelezasdobrasil, @kaleb_aguiar, @embaixadora_dos_ruivos, and @bentomakeup.hair.",
                      "width":  1440,
                      "height":  1920
                  },
                  {
                      "name":  "miss-trabalho-03-foto-02-DSYyoSojTWp.jpg",
                      "file":  "apps\\atelier-kaleb-aguiar\\public\\evidence\\instagram\\relaxed-works\\miss\\03-miss-vitoriabeatrizslv-403-likes-4-fotos-DSYyoSojTWp\\miss-trabalho-03-foto-02-DSYyoSojTWp.jpg",
                      "bytes":  421805,
                      "source":  "https://instagram.fmao1-1.fna.fbcdn.net/v/t51.82787-15/602865207_18089799014476747_4396825193227148800_n.jpg?stp=dst-jpg_e35_tt6\u0026_nc_cat=103\u0026ig_cache_key=Mzc5MDAwMTc0NDg3Nzg0MDc5Mg%3D%3D.3-ccb7-5\u0026ccb=7-5\u0026_nc_sid=58cdad\u0026efg=eyJ2ZW5jb2RlX3RhZyI6IkNBUk9VU0VMX0lURU0ueHBpZHMuMTQ0MC5zZHIucmVndWxhcl9waG90by5DMyJ9\u0026_nc_ohc=GsakgyegyB0Q7kNvwG2GUfc\u0026_nc_oc=Adp9gdnNeJ4GxwbtM8jZ9-yFXw6gNTIpNCuhnPRkyklGuHyeyiRf5O2BfDrS51wrejvdrKhxBJ8Fu8wqDSUqOVCo\u0026_nc_ad=z-m\u0026_nc_cid=0\u0026_nc_zt=23\u0026_nc_ht=instagram.fmao1-1.fna\u0026_nc_gid=7lWsn8VloVAkg8CGImuoVg\u0026_nc_ss=7a22e\u0026oh=00_Af49NAwCojWmSFDHwJAOKEDXa9FRPyWL984QWhZwOI8sCQ\u0026oe=6A1516B1",
                      "alt":  "Photo shared by Vitoria Beatriz on December 17, 2025 tagging @concursobelezasdobrasil, and @concursobelezasdoamazonas.",
                      "width":  1440,
                      "height":  1920
                  },
                  {
                      "name":  "miss-trabalho-03-foto-03-DSYyoSojTWp.jpg",
                      "file":  "apps\\atelier-kaleb-aguiar\\public\\evidence\\instagram\\relaxed-works\\miss\\03-miss-vitoriabeatrizslv-403-likes-4-fotos-DSYyoSojTWp\\miss-trabalho-03-foto-03-DSYyoSojTWp.jpg",
                      "bytes":  94770,
                      "source":  "https://instagram.fmao1-1.fna.fbcdn.net/v/t51.71878-15/658150624_26406443862346530_7619535981298379236_n.jpg?stp=dst-jpg_e15_tt6\u0026_nc_cat=108\u0026ig_cache_key=Mzg2Nzk3ODE5MTEwOTc0MDQ3Ng%3D%3D.3-ccb7-5\u0026ccb=7-5\u0026_nc_sid=58cdad\u0026efg=eyJ2ZW5jb2RlX3RhZyI6IkNMSVBTLnhwaWRzLjY0MC5zZHIudmlkZW9fbmZyYW1lX2NvdmVyX2ZyYW1lLkMzIn0%3D\u0026_nc_ohc=mMxeDfaUCooQ7kNvwGQ7jVH\u0026_nc_oc=Adpkpg4Fi48niATeakTrcHorIWkmKFv3fZzFPptglWvQKQuMXe3L8Oz3NXnvd6ZoHHp_cBHXzOAKR2ZzUGvTJYs8\u0026_nc_ad=z-m\u0026_nc_cid=0\u0026_nc_zt=23\u0026_nc_ht=instagram.fmao1-1.fna\u0026_nc_gid=7lWsn8VloVAkg8CGImuoVg\u0026_nc_ss=7a22e\u0026oh=00_Af5p5T_FhNjfyOAdb0Ng5GtYYNEr9H0KfbYJsyRNkp5p3g\u0026oe=6A153B5B",
                      "alt":  "Aí é emoção \n\n#explorepage✨ #reels #fyp #parque #fy",
                      "width":  640,
                      "height":  1136
                  },
                  {
                      "name":  "miss-trabalho-03-foto-04-DSYyoSojTWp.jpg",
                      "file":  "apps\\atelier-kaleb-aguiar\\public\\evidence\\instagram\\relaxed-works\\miss\\03-miss-vitoriabeatrizslv-403-likes-4-fotos-DSYyoSojTWp\\miss-trabalho-03-foto-04-DSYyoSojTWp.jpg",
                      "bytes":  407088,
                      "source":  "https://instagram.fmao1-1.fna.fbcdn.net/v/t51.82787-15/538027133_18076817105476747_8152515779868048137_n.jpg?stp=dst-jpg_e15_tt6\u0026_nc_cat=104\u0026ig_cache_key=MzcwNTU1MjIxODgzNTUyMDQ0NTE4MDc2ODE3MTAyNDc2NzQ3.3-ccb7-5\u0026ccb=7-5\u0026_nc_sid=58cdad\u0026efg=eyJ2ZW5jb2RlX3RhZyI6IkNMSVBTLnhwaWRzLjIzNDIuc2RyLnZpZGVvX2RlZmF1bHRfY292ZXJfZnJhbWUuQzMifQ%3D%3D\u0026_nc_ohc=73a6ej_Qw44Q7kNvwFg7oMv\u0026_nc_oc=AdpbnOMVgtF_90Y1dmzM8RpTISNRTDXCd_Nd63s-n5540qN3ts7UjICBcVSC4dC_Yo-NLJLydwdCd1tbkgda2w_K\u0026_nc_ad=z-m\u0026_nc_cid=0\u0026_nc_zt=23\u0026_nc_ht=instagram.fmao1-1.fna\u0026_nc_gid=7lWsn8VloVAkg8CGImuoVg\u0026_nc_ss=7a22e\u0026oh=00_Af7JgmpLI2puasD5BjLsjDf57UczPuPL6sG17p8o7onZ1w\u0026oe=6A15329A",
                      "alt":  "O final…😍\n@trendconceptmanaus \n@rodrigosantosbapho \n@amazonasshopping \n\n#explorepage✨ #reels #modelo #fyp #desfile #amazonasfashion",
                      "width":  2342,
                      "height":  4160
                  }
              ]
}
